prism/__init__.py
prism/__version__.py
prism/_docstrings.py
prism/_internal.py
prism/_pipeline.py
prism/_projection.py
prism/_gui/__init__.py
prism/_gui/_globals.py
prism/_gui/core.py
prism/_gui/data/app_icon.ico
prism/_gui/widgets/__init__.py
prism/_gui/widgets/base_layouts.py
prism/_gui/widgets/base_widgets.py
prism/_gui/widgets/conftest.py
prism/_gui/widgets/core.py
prism/_gui/widgets/helpers.py
prism/_gui/widgets/main.py
prism/_gui/widgets/overview.py
prism/_gui/widgets/viewing_area.py
prism/_gui/widgets/preferences/__init__.py
prism/_gui/widgets/preferences/conftest.py
prism/_gui/widgets/preferences/custom_boxes.py
prism/_gui/widgets/preferences/kwargs_dicts.py
prism/_gui/widgets/preferences/options.py
prism/_gui/widgets/preferences/tests/__init__.py
prism/_gui/widgets/preferences/tests/test_custom_boxes.py
prism/_gui/widgets/preferences/tests/test_kwargs_dicts.py
prism/_gui/widgets/preferences/tests/test_options.py
prism/_gui/widgets/tests/__init__.py
prism/_gui/widgets/tests/test_base_widgets.py
prism/_gui/widgets/tests/test_core.py
prism/_gui/widgets/tests/test_helpers.py
prism/_gui/widgets/tests/test_main.py
prism/_gui/widgets/tests/test_overview.py
prism/data/data_gaussian.txt
prism/data/data_sine_wave.txt
prism/data/parameters_gaussian.txt
prism/data/parameters_sine_wave.txt
prism/data/prism.txt
prism/emulator/__init__.py
prism/emulator/_emulator.py
prism/modellink/__init__.py
prism/modellink/_gaussian_link.py
prism/modellink/_modellink.py
prism/modellink/_poly_link.py
prism/modellink/_sine_wave_link.py
prism/modellink/utils.py
prism/modellink/tests/__init__.py
prism/modellink/tests/test_gaussian_link.py
prism/modellink/tests/test_modellink.py
prism/modellink/tests/test_poly_link.py
prism/modellink/tests/test_sine_wave_link.py
prism/modellink/tests/test_utils.py
prism/modellink/tests/data/data_gaussian.txt
prism/modellink/tests/data/data_gaussian_double.txt
prism/modellink/tests/data/data_gaussian_single.txt
prism-1.3.2.dist-info/LICENSE
prism-1.3.2.dist-info/METADATA
prism-1.3.2.dist-info/WHEEL
prism-1.3.2.dist-info/top_level.txt
prism-1.3.2.dist-info/RECORD
