Metadata-Version: 2.1
Name: prism
Version: 1.3.2
Summary: PRISM: An alternative to MCMC for rapid analysis of models
Home-page: https://prism-tool.readthedocs.io/en/latest
Author: Ellert van der Velden
Author-email: evandervelden@swin.edu.au
Maintainer: 1313e
License: BSD-3
Download-URL: https://github.com/1313e/PRISM/archive/v1.3.2.zip
Project-URL: Documentation, https://prism-tool.readthedocs.io/en/v1.3.2
Project-URL: Method Paper, https://arxiv.org/abs/1901.08725
Project-URL: Source Code, https://github.com/1313e/PRISM/tree/v1.3.2
Keywords: prism model analysis emulator regression mcmc optimization
Platform: Windows
Platform: Mac OS-X
Platform: Linux
Platform: Unix
Classifier: Development Status :: 5 - Production/Stable
Classifier: Intended Audience :: Developers
Classifier: Intended Audience :: Science/Research
Classifier: License :: OSI Approved :: BSD License
Classifier: Natural Language :: English
Classifier: Operating System :: MacOS
Classifier: Operating System :: Microsoft :: Windows
Classifier: Operating System :: Unix
Classifier: Programming Language :: Python
Classifier: Programming Language :: Python :: 3
Classifier: Programming Language :: Python :: 3.6
Classifier: Programming Language :: Python :: 3.7
Classifier: Programming Language :: Python :: 3.8
Classifier: Topic :: Scientific/Engineering
Classifier: Topic :: Software Development
Requires-Python: >=3.6, <4
Requires-Dist: cmasher (>=1.0.5)
Requires-Dist: e13tools (>=0.9.1)
Requires-Dist: h5py (<3.0.0,>=2.8.0)
Requires-Dist: hickle (>=3.4.0)
Requires-Dist: matplotlib (>=2.2.4)
Requires-Dist: mlxtend (>=0.16.0)
Requires-Dist: mpi4pyd (>=0.3.1)
Requires-Dist: numpy (>=1.16.0)
Requires-Dist: pyqt5 (==5.12.*)
Requires-Dist: qtpy (>=1.9.0)
Requires-Dist: scikit-learn (>=0.22)
Requires-Dist: scipy (>=1.0.0)
Requires-Dist: sortedcontainers (>=1.5.9)
Requires-Dist: threadpoolctl (>=1.0.0)
Requires-Dist: tqdm (>=4.7.6)
